LICENSE.txt
README.md
setup.cfg
setup.py
src/EIMTC/__init__.py
src/EIMTC/cli.py
src/EIMTC/extractor.py
src/EIMTC/tls_tshark_entry.py
src/EIMTC/utils.py
src/EIMTC/metrics/__init__.py
src/EIMTC/metrics/_detection.py
src/EIMTC/metrics/_multi_label.py
src/EIMTC/modals/__init__.py
src/EIMTC/modals/_graph2vec.py
src/EIMTC/modals/_graph2vec_stnnft.py
src/EIMTC/modals/_graphdapp.py
src/EIMTC/modals/_lopez_protocol_header_fields.py
src/EIMTC/modals/_lopez_protocol_header_fields_TDL.py
src/EIMTC/modals/_lopez_protocol_header_fields_extended.py
src/EIMTC/modals/_modal_wrapper.py
src/EIMTC/modals/_stft.py
src/EIMTC/modals/_stnn.py
src/EIMTC/modals/_stnn_extended.py
src/EIMTC/modals/_utils.py
src/EIMTC/modals/_wang_payload.py
src/EIMTC/modals/_wavelet.py
src/EIMTC/models/__init__.py
src/EIMTC/models/_chainedgnn.py
src/EIMTC/models/_custom_distiller.py
src/EIMTC/models/_deepmal.py
src/EIMTC/models/_distiller.py
src/EIMTC/models/_graphdapp.py
src/EIMTC/models/_hybrid.py
src/EIMTC/models/_m1cnn.py
src/EIMTC/models/_maldist.py
src/EIMTC/models/_model_wrapper.py
src/EIMTC/plugins/__init__.py
src/EIMTC/plugins/_stnnft.py
src/EIMTC/plugins/asn_info.py
src/EIMTC/plugins/clumps_flow.py
src/EIMTC/plugins/clumps_flow_timeframe.py
src/EIMTC/plugins/dns_counter.py
src/EIMTC/plugins/first_packet_payload.py
src/EIMTC/plugins/flowpic.py
src/EIMTC/plugins/graypic.py
src/EIMTC/plugins/most_freq_payload_len_ratio.py
src/EIMTC/plugins/n_bytes.py
src/EIMTC/plugins/n_bytes_per_packet.py
src/EIMTC/plugins/n_pkts_byte_freq.py
src/EIMTC/plugins/packets_size_interarrival_time.py
src/EIMTC/plugins/pkt_rel_time.py
src/EIMTC/plugins/protocol_header_fields.py
src/EIMTC/plugins/protocol_header_fields_TDL.py
src/EIMTC/plugins/protocol_header_fields_extended.py
src/EIMTC/plugins/recv_sent_pkt_ratio.py
src/EIMTC/plugins/res_req_diff_time.py
src/EIMTC/plugins/simple_tig.py
src/EIMTC/plugins/small_pkt_payload_ratio.py
src/EIMTC/plugins/stnn.py
src/EIMTC/plugins/stnn_extended.py
src/EIMTC/plugins/stnn_timeframe.py
src/OSF_EIMTC.egg-info/PKG-INFO
src/OSF_EIMTC.egg-info/SOURCES.txt
src/OSF_EIMTC.egg-info/dependency_links.txt
src/OSF_EIMTC.egg-info/requires.txt
src/OSF_EIMTC.egg-info/top_level.txt