Metadata-Version: 2.1
Name: OSF-EIMTC
Version: 0.1.61
Summary: A Framework for Encrypted Internet and Malicious Traffic Classification.
Home-page: https://github.com/ArielCyber/OSF-EIMTC/
Author: Ariel University
Author-email: chenha@ariel.ac.il
License: MIT
Keywords: nfstream,pcap,network,deep-learning,extraction
Platform: UNKNOWN
